odoo/addons/switchboard_somconnexio/CHANGELOG.md
odoo/addons/switchboard_somconnexio/README.rst
odoo/addons/switchboard_somconnexio/__init__.py
odoo/addons/switchboard_somconnexio/__manifest__.py
odoo/addons/switchboard_somconnexio/data/product_attribute.xml
odoo/addons/switchboard_somconnexio/data/product_attribute_value.xml
odoo/addons/switchboard_somconnexio/data/product_category.xml
odoo/addons/switchboard_somconnexio/data/product_category_technology_supplier_data.xml
odoo/addons/switchboard_somconnexio/data/product_template_attribute_line_data.xml
odoo/addons/switchboard_somconnexio/data/product_template_data.xml
odoo/addons/switchboard_somconnexio/data/service_supplier.xml
odoo/addons/switchboard_somconnexio/data/service_technology.xml
odoo/addons/switchboard_somconnexio/data/service_technology_service_supplier.xml
odoo/addons/switchboard_somconnexio/data/products/switchboard.xml
odoo/addons/switchboard_somconnexio/demo/contract.xml
odoo/addons/switchboard_somconnexio/i18n/ca_ES.po
odoo/addons/switchboard_somconnexio/i18n/es.po
odoo/addons/switchboard_somconnexio/migrations/16.0.1.0.1/post-migrate-sb-products.py
odoo/addons/switchboard_somconnexio/migrations/16.0.1.0.1/pre-migrate-sb-products.py
odoo/addons/switchboard_somconnexio/migrations/16.0.1.0.2/post-migrate-set-external-provisioning-sb-tech.py
odoo/addons/switchboard_somconnexio/models/__init__.py
odoo/addons/switchboard_somconnexio/models/contract_contract.py
odoo/addons/switchboard_somconnexio/models/crm_lead.py
odoo/addons/switchboard_somconnexio/models/crm_lead_line.py
odoo/addons/switchboard_somconnexio/models/contract_info/__init__.py
odoo/addons/switchboard_somconnexio/models/contract_info/switchboard_service_contract_info.py
odoo/addons/switchboard_somconnexio/models/isp_info/__init__.py
odoo/addons/switchboard_somconnexio/models/isp_info/switchboard_isp_info.py
odoo/addons/switchboard_somconnexio/security/ir.model.access.csv
odoo_addon_switchboard_somconnexio-16.0.1.0.4.dist-info/METADATA
odoo_addon_switchboard_somconnexio-16.0.1.0.4.dist-info/WHEEL
odoo_addon_switchboard_somconnexio-16.0.1.0.4.dist-info/top_level.txt
odoo_addon_switchboard_somconnexio-16.0.1.0.4.dist-info/RECORD
